[{"__symbolic":"module","version":3,"metadata":{"FeedbackModule":{"__symbolic":"class","decorators":[{"__symbolic":"call","expression":{"__symbolic":"reference","module":"@angular/core","name":"NgModule"},"arguments":[{"imports":[{"__symbolic":"reference","module":"@angular/common","name":"CommonModule"},{"__symbolic":"reference","module":"@angular/forms","name":"FormsModule"},{"__symbolic":"reference","module":"@angular/forms","name":"ReactiveFormsModule"}],"declarations":[{"__symbolic":"reference","module":"./feedback.component","name":"FeedbackComponent"}],"exports":[{"__symbolic":"reference","module":"./feedback.component","name":"FeedbackComponent"}]}]}]}}},{"__symbolic":"module","version":1,"metadata":{"FeedbackModule":{"__symbolic":"class","decorators":[{"__symbolic":"call","expression":{"__symbolic":"reference","module":"@angular/core","name":"NgModule"},"arguments":[{"imports":[{"__symbolic":"reference","module":"@angular/common","name":"CommonModule"},{"__symbolic":"reference","module":"@angular/forms","name":"FormsModule"},{"__symbolic":"reference","module":"@angular/forms","name":"ReactiveFormsModule"}],"declarations":[{"__symbolic":"reference","module":"./feedback.component","name":"FeedbackComponent"}],"exports":[{"__symbolic":"reference","module":"./feedback.component","name":"FeedbackComponent"}]}]}]}}}]